dealcards/__init__.py
dealcards/static/widget-copy.js
dealcards/static/widget.css
dealcards/static/widget.js
dealcards-0.0.1.dist-info/METADATA
dealcards-0.0.1.dist-info/WHEEL
dealcards-0.0.1.dist-info/licenses/LICENSE
dealcards-0.0.1.dist-info/RECORD
